ProbabilisticSymptomGraph/ProbabilisticSymptomConditionGraph.py
ProbabilisticSymptomGraph/__init__.py
probabilistic_symptom_graph-1.0.3.dist-info/LICENSE
probabilistic_symptom_graph-1.0.3.dist-info/METADATA
probabilistic_symptom_graph-1.0.3.dist-info/WHEEL
probabilistic_symptom_graph-1.0.3.dist-info/top_level.txt
probabilistic_symptom_graph-1.0.3.dist-info/RECORD
