Metadata-Version: 2.1
Name: probabilistic-symptom-graph
Version: 1.0.3
Summary: Using a bipartite graph of medical conditions and symptoms with relative weighted edges, gives the estimated probability of having each illness given a list of symptoms
Author-email: Bart Gebka <bartg1259@gmail.com>
License: MIT License
Keywords: graph,medicine,healthcare,prediction,probability
Classifier: License :: OSI Approved :: MIT License
Classifier: Programming Language :: Python
Classifier: Programming Language :: Python :: 3
Requires-Python: >=3.8
License-File: LICENSE
Requires-Dist: networkx
Requires-Dist: numpy
Provides-Extra: dev
